old_attempt/verilog/instruction_reg.v
module instructionReg (
    input [0:25] dataIn,
    input load,
    output [0:25] dataOut
);
    reg [0:25] register;
    assign dataOut = register;

    always @(posedge load)
        register <=dataIn;
endmodule

// Testbench
// module instructionReg_tb;
//     reg [0:25] dataIn;
//     reg load;
//     wire [0:25] dataOut;

//     instructionReg instructionReg1 (
//         .dataIn(dataIn),
//         .load(load),
//         .dataOut(dataOut)
//     );

//     initial begin
//         $monitor("dataIn = %b load = %b dataOut = %b", dataIn, load, dataOut);

//         dataIn = 4;
//         load = 0;
//         #5
//         load = 1;
//     end
// endmodule

old_attempt/verilog/program_counter.v
module programCounter (
    input [0:15] data,
    input load, clk, reset,
    output [0:15] count
);
    reg [0:15] counterReg;
    assign count = counterReg;

    initial
        counterReg <= 0;

    always @(posedge clk or posedge reset) begin
        if(reset)
            counterReg <= 16'd0;
        else
            if (load)
                counterReg <= data;
            else
                counterReg <= counterReg + 16'd1;
    end
endmodule

// Testbench
// module programCounter_tb;
//     reg load, clk, reset;
//     reg [0:15] data;
//     wire [0:15] counter;

//     programCounter programCounter_1(
//         .data(data),
//         .load(load),
//         .clk(clk),
//         .reset(reset),
//         .counter(counter)
//     );

//     initial begin
//         $monitor("counter = %b\n", counter);
//         data = 0;
//         load = 0;
//         reset = 1;
//         #5
//         reset = 0;
//         clk = 0;
//         forever #5 clk = !clk;
//     end
// endmodule

old_attempt/verilog/alu.v
module alu (
    input [0:15] a,
    input [0:15] b,
    input [0:2] select,
    input enable,
    output [0:15] out,
    output carry
);
    reg [0:15] result;
    wire [0:16] tmp;

    assign tmp = {a, 1'b0} + {b, 1'b0};
    assign carry = tmp[16];
    assign out = result;

    always @(enable) begin
        case (select)
            3'b000:
                result <= a + b;
            3'b001:
                result <= a - b;
            3'b010:
                result <= a ^ b;
            3'b011:
                result <= a & b;
        endcase
    end
endmodule

// Testbench
// module alu_tb;
//     reg [0:15] A, B;
//     reg [0:2] select;
//     reg en;
//     wire [0:15] result;
//     wire carry;

//     alu alu1(
//         .a(A),
//         .b(B),
//         .select(select),
//         .enable(en),
//         .out(result),
//         .carry(carry) 
//     );

//     initial begin

//         $monitor("enable=%b a=%b b=%b \nselect=%b result=%b carry=%b\n\n",
//                 en, A, B, select, result, carry);
    
//         A = 2;
//         B = 2;
//         en = 1;
//         select = 0;
//         #5
//         en = 0;
//         en = 1;
//         select = 1;
//         #5
//         en = 0;
//         en = 1;
//         select = 2;
//         #5
//         en = 0;
//         en = 1;
//         select = 3;
//     end
// endmodule

old_attempt/verilog/memory.v
module memory (
    input load,
    input [0:25] dataIn,
    input [0:15] address,
    output reg [0:25] dataOut
);
    reg [0:25] memoryArray [0:65535];

    initial // Load program
        $readmemb("program.bin", memoryArray, 0, 0);

    always @(*) begin
        if (load)
            memoryArray[address] <= dataIn;

        dataOut <= memoryArray[address];
    end
endmodule

old_attempt/verilog/register_file.v
module regFile (
    input [0:2] sel1,       // Select for dataOut1
    input [0:2] sel2,       // Select for dataOut2
    input [0:2] dataSel,    // Select for register to write to
    input [0:15] dataIn,    // Data in
    input load,             // Enable output
    output [0:15] dataOut1, // Data output for sel1
    output [0:15] dataOut2  // Data output for sel2
);
    reg [0:15] regArray [0:7];
    integer i;

    initial begin
        $dumpvars(0, regFile);
        for (i = 0; i < 8; i = i + 1)
            regArray[i] <= 0;

        $monitor("r0 = %b\nr1 = %b\nr2 = %b\nr3 = %b\nr4 = %b\nr5 = %b\nr6 = %b\nr7 = %b\n\n",
                regArray[0], regArray[1], regArray[2], regArray[3], regArray[4], regArray[5],
                regArray[6], regArray[7]);
    end

    assign dataOut1 = regArray[sel1];
    assign dataOut2 = regArray[sel2];

    always @(posedge load)
        regArray[dataSel] <= dataIn;

endmodule

// Tesbench
// module registerFile_tb;
//     reg [0:2] sel1, sel2, dataSel;
//     reg [0:15] dataIn;
//     reg load;

//     wire [0:15] dataOut1, dataOut2;

//     regFile regFile1 (
//         .sel1(sel1),
//         .sel2(sel2),
//         .dataSel(dataSel),
//         .dataIn(dataIn),
//         .load(load),
//         .dataOut1(dataOut1),
//         .dataOut2(dataOut2)
//     );

//     initial begin
//         $monitor("sel1 = %b sel2 = %b dataSel = %b\ndataIn = %b load = %b\n\ndataOut1 = %b dataOut2 = %b\n",
//                 sel1, sel2, dataSel, dataIn, load, dataOut1, dataOut2);
//         sel1 = 1;
//         dataSel = 1;
//         dataIn = 3;
//         load = 1;
//     end
// endmodule

old_attempt/verilog/control_unit.v
module controlUnit (
    input clk,
    input aluCarry,
    input [0:25] instruction,
    input [0:15] aluOut, regDataOut1, regDataOut2,
    output reg aluEnable, regLoad, instrLoad, pcClk,
    output reg [0:2] aluSel, regSel1, regSel2, regSelData,
    output reg [0:15] aluA, aluB, regDataIn
);
    reg [0:1] cycle;

    initial begin
        $dumpfile("dump.vcd");
        $dumpvars(1, controlUnit, calcu16);
        cycle <= 0;
    end

    always @(posedge clk) begin
        case (cycle)
            2'b00: begin // Cycle 0
                // Load the instruction register with the instr stored in ram
                instrLoad <= 1;
                end
            2'b01: begin // Cycle 1
                instrLoad <= 0;
                pcClk <= 1; // Increment the program counter
                case (instruction[0:3])
                    4'b0001: begin // ADD
                        regSel1 <= instruction[7:9];
                        regSel2 <= instruction[10:12];
                        aluA <= regDataOut1;
                        aluB <= regDataOut2;
                        aluSel <= 0;
                        aluEnable <= 1;
                        regSelData <= instruction[4:6];
                        regDataIn <= aluOut;
                    end
                    4'b0010: begin // ADDI
                        regSel1 <= instruction[7:9];
                        aluB <= instruction[10:25];
                        aluA <= regDataOut1[0:15];
                        aluSel <= 0;
                        aluEnable <= 1;
                        regSelData <= instruction[4:6];
                        regDataIn <= aluOut;
                    end
                endcase

                end
            2'b10: begin // Cycle 2
                pcClk <= 0; // Reset pc clk
                case (instruction[0:3])
                    4'b0001: begin // ADD
                        regLoad <= 1;
                    end
                    4'b0010: begin // ADDI
                        regLoad <= 1;
                    end
                endcase
            end
            2'b11: begin // Cycle 3
                case (instruction[0:3])
                    4'b0001: begin // ADD
                        regLoad <= 0;
                        aluEnable <= 0;
                    end
                    4'b0010: begin // ADDI
                        regLoad <= 0;
                        aluEnable <= 0;
                    end
                endcase
            end
        endcase
        cycle <= cycle + 1;

    end
endmodule

old_attempt/verilog/calcu-16.v
module calcu16 (
    input clk
);
    wire [0:25] instruction, memDataOut;
    wire aluCarry, aluEnable, regLoad, instrLoad, pcClk;
    wire [0:2] aluSel, regSel1, regSel2, regSelData;
    wire [0:15] aluOut, regDataOut1, regDataOut2, aluA, aluB, regDataIn, address;

    controlUnit ctrlUnit (
        .clk(clk),
        .aluCarry(aluCarry),
        .instruction(instruction),
        .aluOut(aluOut),
        .regDataOut1(regDataOut1),
        .regDataOut2(regDataOut2),
        .aluEnable(aluEnable),
        .regLoad(regLoad),
        .instrLoad(instrLoad),
        .pcClk(pcClk),
        .aluSel(aluSel),
        .regSel1(regSel1),
        .regSel2(regSel2),
        .regSelData(regSelData),
        .aluA(aluA),
        .aluB(aluB),
        .regDataIn(regDataIn)
    );
    
    regFile registerFile (
        .sel1(regSel1),
        .sel2(regSel2),
        .dataSel(regSelData),
        .dataIn(regDataIn),
        .load(regLoad),
        .dataOut1(regDataOut1),
        .dataOut2(regDataOut2)
    );

    memory RAM (
        .load(),
        .dataIn(),
        .address(address),
        .dataOut(memDataOut)
    );
    
    alu ALU (
        .a(aluA),
        .b(aluB),
        .select(aluSel),
        .enable(aluEnable),
        .out(aluOut),
        .carry(aluCarry)
    );

    programCounter PC (
        .data(),
        .load(),
        .clk(pcClk),
        .count(address)
    );
    
    instructionReg IR (
        .dataIn(memDataOut),
        .load(instrLoad),
        .dataOut(instruction)
    );
endmodule

old_attempt/verilog/calcu-16_tb.v
`define simulation_time #160

module calcu16_tb;
    reg clk;

    calcu16 processor (
        .clk(clk)
    );

    initial begin
        clk <= 1;
        `simulation_time;
        $finish;
    end

    always
        #5 clk = ~clk;

endmodule

old_attempt/dump.vcd
$date
	Sat Jan 12 18:12:24 2019
$end
$version
	Icarus Verilog
$end
$timescale
	1s
$end
$scope module calcu16_tb $end
$scope module processor $end
$scope module ctrlUnit $end
$var wire 1 ! aluCarry $end
$var wire 16 " aluOut [0:15] $end
$var wire 1 # clk $end
$var wire 26 $ instruction [0:25] $end
$var wire 16 % regDataOut2 [0:15] $end
$var wire 16 & regDataOut1 [0:15] $end
$var reg 16 ' aluA [0:15] $end
$var reg 16 ( aluB [0:15] $end
$var reg 1 ) aluEnable $end
$var reg 3 * aluSel [0:2] $end
$var reg 2 + cycle [0:1] $end
$var reg 1 , instrLoad $end
$var reg 1 - pcClk $end
$var reg 16 . regDataIn [0:15] $end
$var reg 1 / regLoad $end
$var reg 3 0 regSel1 [0:2] $end
$var reg 3 1 regSel2 [0:2] $end
$var reg 3 2 regSelData [0:2] $end
$upscope $end
$upscope $end
$upscope $end
$scope module calcu16_tb $end
$scope module processor $end
$var wire 1 # clk $end
$var wire 3 3 regSelData [0:2] $end
$var wire 3 4 regSel2 [0:2] $end
$var wire 3 5 regSel1 [0:2] $end
$var wire 1 / regLoad $end
$var wire 16 6 regDataOut2 [0:15] $end
$var wire 16 7 regDataOut1 [0:15] $end
$var wire 16 8 regDataIn [0:15] $end
$var wire 1 - pcClk $end
$var wire 26 9 memDataOut [0:25] $end
$var wire 26 : instruction [0:25] $end
$var wire 1 , instrLoad $end
$var wire 3 ; aluSel [0:2] $end
$var wire 16 < aluOut [0:15] $end
$var wire 1 ) aluEnable $end
$var wire 1 ! aluCarry $end
$var wire 16 = aluB [0:15] $end
$var wire 16 > aluA [0:15] $end
$var wire 16 ? address [0:15] $end
$upscope $end
$upscope $end
$scope module calcu16_tb $end
$scope module processor $end
$scope module registerFile $end
$var wire 16 @ dataIn [0:15] $end
$var wire 16 A dataOut1 [0:15] $end
$var wire 16 B dataOut2 [0:15] $end
$var wire 3 C dataSel [0:2] $end
$var wire 1 / load $end
$var wire 3 D sel1 [0:2] $end
$var wire 3 E sel2 [0:2] $end
$var integer 32 F i [31:0] $end
$upscope $end
$upscope $end
$upscope $end
$enddefinitions $end
#0
$dumpvars
b1000 F
bx E
bx D
bx C
bx B
bx A
bx @
b0 ?
bx >
bx =
bx <
bx ;
b10000000000000000000000 :
b10000000000000000000000 9
bx 8
bx 7
bx 6
bx 5
bx 4
bx 3
bx 2
bx 1
bx 0
x/
bx .
x-
1,
b1 +
bx *
x)
bx (
bx '
bx &
bx %
b10000000000000000000000 $
1#
bx "
x!
$end
#5
0#
#10
bx 9
b1 ?
b10 +
b0 2
b0 3
b0 C
1)
b0 *
b0 ;
b0 %
b0 6
b0 B
b0 1
b0 4
b0 E
b0 &
b0 7
b0 A
b0 0
b0 5
b0 D
1-
0,
1#
#15
0#
#20
bx &
bx 7
bx A
bx %
bx 6
bx B
b11 +
1/
0-
1#
#25
0#
#30
b0 +
0)
0/
1#
#35
0#
#40
bx $
bx :
b1 +
1,
1#
#45
0#
#50
b10 ?
b10 +
1-
0,
1#
#55
0#
#60
b11 +
0-
1#
#65
0#
#70
b0 +
1#
#75
0#
#80
b1 +
1,
1#
#85
0#
#90
b11 ?
b10 +
1-
0,
1#
#95
0#
#100
b11 +
0-
1#
#105
0#
#110
b0 +
1#
#115
0#
#120
b1 +
1,
1#
#125
0#
#130
b100 ?
b10 +
1-
0,
1#
#135
0#
#140
b11 +
0-
1#
#145
0#
#150
b0 +
1#
#155
0#
#160
b1 +
1,
1#
